{
  "injections": {
    "__dataframe__": true,
    "content": {
      "simulation_id": [
        0
      ],
      "luminosity_distance": [
        173.03911309431928
      ],
      "timeshift": [
        0.6449840101844185
      ],
      "inclination_EM": [
        0.15431052858100042
      ],
      "log10_E0": [
        53.0
      ],
      "thetaCore": [
        0.05
      ],
      "thetaWing": [
        0.1
      ],
      "log10_n0": [
        0.47604370317613576
      ],
      "p": [
        2.7959788555853944
      ],
      "log10_epsilon_e": [
        -1.4218088923248557
      ],
      "log10_epsilon_B": [
        -2.3662840581402946
      ],
      "ksiN": [
        1.0
      ],
      "L0": [
        0.0
      ],
      "dL": [
        3.09e+19
      ],
      "b": [
        6.0
      ],
      "q": [
        0.0
      ],
      "ts": [
        0.0
      ],
      "geocent_time": [
        -0.09727140935658829
      ]
    }
  }
}