{
  "injections": {
    "__dataframe__": true,
    "content": {
      "simulation_id": [
        0
      ],
      "luminosity_distance": [
        161.69915352955266
      ],
      "timeshift": [
        -0.07640192248385773
      ],
      "inclination_EM": [
        0.07742375959402889
      ],
      "log10_E0": [
        53.0
      ],
      "thetaCore": [
        0.05
      ],
      "thetaWing": [
        0.1
      ],
      "log10_n0": [
        0.8162697936608891
      ],
      "p": [
        2.122553156016755
      ],
      "log10_epsilon_e": [
        -0.6961433106037718
      ],
      "log10_epsilon_B": [
        -2.2586878246734696
      ],
      "ksiN": [
        1.0
      ],
      "L0": [
        0.0
      ],
      "dL": [
        3.09e+19
      ],
      "b": [
        6.0
      ],
      "q": [
        0.0
      ],
      "ts": [
        0.0
      ],
      "geocent_time": [
        0.06440415675851013
      ]
    }
  }
}