{
    "luminosity_distance": 182.5045118273929,
    "beta": 3.1078325195649343,
    "log10_kappa_r": 0.6440964114873058,
    "KNtimeshift": -1.257596567932941,
    "log10_vej": -1.9548804340848644,
    "log10_mej": -2.2955285139067723,
    "Ebv": 0.534659524187391,
    "log_likelihood": -8.634215162418593,
    "log_prior": -11.67163263330075,
    "Best fit index": 3641,
    "Magnitudes": {
        "ztfg": [
            27.425885417162895,
            25.073973191903498,
            24.283711821743417,
            23.360541109024616,
            22.703734752529876,
            22.196150795698657,
            21.810444367755856,
            21.55950997390594,
            21.37945401339902,
            21.291696057118337,
            Infinity
        ],
        "bestfit_sample_times": [
            0.1,
            0.6,
            1.1,
            1.6,
            2.1,
            2.6,
            3.1,
            3.6,
            4.1,
            4.6,
            5.1
        ]
    }
}